{
  "bomFormat": "GridForge-SBOM",
  "specVersion": "1.0",
  "version": 1,
  "metadata": {
    "timestamp": "2026-05-05T23:40:11.281053+00:00",
    "component": {
      "name": "gridforge",
      "version": "0.1.0",
      "type": "application"
    },
    "tools": [
      {
        "name": "gridforge-sbom-gen",
        "version": "1.0"
      }
    ]
  },
  "components": [
    {
      "name": "gridforge",
      "version": "0.1.0",
      "ecosystem": "pypi",
      "type": "internal-library",
      "source": "pyproject.toml"
    },
    {
      "name": "gridforge-adapter-eia",
      "version": "0.1.0",
      "ecosystem": "pypi",
      "type": "internal-library",
      "source": "packages/adapters/eia/pyproject.toml"
    },
    {
      "name": "gridforge-adapter-entsoe",
      "version": "0.1.0",
      "ecosystem": "pypi",
      "type": "internal-library",
      "source": "packages/adapters/entsoe/pyproject.toml"
    },
    {
      "name": "gridforge-adapter-nasa-power",
      "version": "0.1.0",
      "ecosystem": "pypi",
      "type": "internal-library",
      "source": "packages/adapters/nasa_power/pyproject.toml"
    },
    {
      "name": "gridforge-adapter-noaa-nws",
      "version": "0.1.0",
      "ecosystem": "pypi",
      "type": "internal-library",
      "source": "packages/adapters/noaa_nws/pyproject.toml"
    },
    {
      "name": "gridforge-adapter-nrel",
      "version": "0.1.0",
      "ecosystem": "pypi",
      "type": "internal-library",
      "source": "packages/adapters/nrel/pyproject.toml"
    },
    {
      "name": "gridforge-adapter-open-meteo",
      "version": "0.1.0",
      "ecosystem": "pypi",
      "type": "internal-library",
      "source": "packages/adapters/open_meteo/pyproject.toml"
    },
    {
      "name": "gridforge-anomaly",
      "version": "0.1.0",
      "ecosystem": "pypi",
      "type": "internal-library",
      "source": "packages/anomaly/pyproject.toml"
    },
    {
      "name": "gridforge-api",
      "version": "0.1.0",
      "ecosystem": "pypi",
      "type": "internal-library",
      "source": "apps/api/pyproject.toml"
    },
    {
      "name": "gridforge-dispatch",
      "version": "0.1.0",
      "ecosystem": "pypi",
      "type": "internal-library",
      "source": "packages/dispatch/pyproject.toml"
    },
    {
      "name": "gridforge-domain",
      "version": "0.1.0",
      "ecosystem": "pypi",
      "type": "internal-library",
      "source": "packages/domain/pyproject.toml"
    },
    {
      "name": "gridforge-forecasting",
      "version": "0.1.0",
      "ecosystem": "pypi",
      "type": "internal-library",
      "source": "packages/forecasting/pyproject.toml"
    },
    {
      "name": "gridforge-predictive",
      "version": "0.1.0",
      "ecosystem": "pypi",
      "type": "internal-library",
      "source": "packages/predictive/pyproject.toml"
    },
    {
      "name": "gridforge-recommendations",
      "version": "0.1.0",
      "ecosystem": "pypi",
      "type": "internal-library",
      "source": "packages/recommendations/pyproject.toml"
    },
    {
      "name": "gridforge-simulation",
      "version": "0.1.0",
      "ecosystem": "pypi",
      "type": "internal-library",
      "source": "packages/simulation/pyproject.toml"
    },
    {
      "name": "fastapi",
      "version": "0.136.1",
      "ecosystem": "pypi",
      "type": "library"
    },
    {
      "name": "httpx",
      "version": "0.28.1",
      "ecosystem": "pypi",
      "type": "library"
    },
    {
      "name": "pydantic",
      "version": "2.13.3",
      "ecosystem": "pypi",
      "type": "library"
    },
    {
      "name": "pydantic-settings",
      "version": "2.14.0",
      "ecosystem": "pypi",
      "type": "library"
    },
    {
      "name": "@types/react",
      "version": "18.2.0",
      "ecosystem": "npm",
      "type": "library"
    },
    {
      "name": "@types/react-dom",
      "version": "18.2.0",
      "ecosystem": "npm",
      "type": "library"
    },
    {
      "name": "@vitejs/plugin-react",
      "version": "4.1.0",
      "ecosystem": "npm",
      "type": "library"
    },
    {
      "name": "axios",
      "version": "1.16.0",
      "ecosystem": "npm",
      "type": "library"
    },
    {
      "name": "react",
      "version": "18.3.1",
      "ecosystem": "npm",
      "type": "library"
    },
    {
      "name": "react-dom",
      "version": "18.3.1",
      "ecosystem": "npm",
      "type": "library"
    },
    {
      "name": "react-router-dom",
      "version": "6.30.3",
      "ecosystem": "npm",
      "type": "library"
    },
    {
      "name": "recharts",
      "version": "2.15.4",
      "ecosystem": "npm",
      "type": "library"
    },
    {
      "name": "typescript",
      "version": "5.9.3",
      "ecosystem": "npm",
      "type": "library"
    },
    {
      "name": "vite",
      "version": "5.4.21",
      "ecosystem": "npm",
      "type": "library"
    }
  ]
}